licheepi/__init__.py
licheepi-0.0.0.dist-info/DESCRIPTION.rst
licheepi-0.0.0.dist-info/METADATA
licheepi-0.0.0.dist-info/RECORD
licheepi-0.0.0.dist-info/WHEEL
licheepi-0.0.0.dist-info/metadata.json
licheepi-0.0.0.dist-info/top_level.txt
