Metadata-Version: 2.1
Name: licheepi
Version: 0.0.0
Summary: licheepi
Home-page: https://github.com/licheepi/pip-licheepi
Author: alan
Author-email: alan@licheepi.com
License: UNKNOWN
Platform: UNKNOWN
Classifier: Programming Language :: Python :: 2.7
Classifier: Programming Language :: Python :: 3.5
Classifier: Programming Language :: Python :: 3.6
Classifier: Programming Language :: Python :: 3.7
Classifier: License :: OSI Approved :: BSD License
Classifier: Operating System :: OS Independent
